ttrack/__init__.py
ttrack/ttrack_cpp.so
tiny_track-0.0.3.dist-info/METADATA
tiny_track-0.0.3.dist-info/WHEEL
tiny_track-0.0.3.dist-info/top_level.txt
tiny_track-0.0.3.dist-info/RECORD
tiny_track-0.0.3.dist-info/licenses/LICENSE
